pygnn/VERSION.txt
pygnn/__init__.py
pygnn/__main__.py
pygnn-0.0.1.dist-info/METADATA
pygnn-0.0.1.dist-info/WHEEL
pygnn-0.0.1.dist-info/top_level.txt
pygnn-0.0.1.dist-info/zip-safe
pygnn-0.0.1.dist-info/RECORD
